{
  "variant": "ie",
  "variant_name": "Inland Empire",
  "maxsp": 23,
  "files_parsed": [
    "blkdat.f90",
    "crown.f90",
    "dgf.f90",
    "htgf.f90",
    "sitset.f90"
  ],
  "categories": {
    "growth": {
      "WEIBB1": [
        0.0,
        0.0,
        0.0,
        0.0,
        0.0,
        0.0,
        0.0,
        0.0,
        0.0,
        0.0,
        0.0,
        0.0,
        1.06217,
        0.0,
        0.0,
        0.0,
        1.06217,
        1.14765,
        0.0,
        1.14765,
        1.14765,
        0.0,
        0.0
      ]
    },
    "species_definitions": {
      "JTYPE": [
        10.0,
        100.0,
        110.0,
        130.0,
        140.0,
        160.0,
        170.0,
        180.0,
        190.0,
        200.0,
        210.0,
        220.0,
        230.0,
        250.0,
        260.0,
        280.0,
        290.0,
        310.0,
        320.0,
        330.0,
        340.0,
        350.0,
        360.0,
        370.0,
        380.0,
        400.0,
        410.0,
        420.0,
        430.0,
        440.0,
        450.0,
        460.0,
        470.0,
        480.0,
        500.0,
        501.0,
        502.0,
        505.0,
        506.0,
        510.0,
        515.0,
        516.0,
        520.0,
        529.0,
        530.0,
        540.0,
        545.0,
        550.0,
        555.0,
        560.0,
        565.0,
        570.0,
        575.0,
        579.0,
        590.0,
        600.0,
        610.0,
        620.0,
        630.0,
        635.0,
        640.0,
        650.0,
        660.0,
        670.0,
        675.0,
        680.0,
        685.0,
        690.0,
        700.0,
        701.0,
        710.0,
        720.0,
        730.0,
        740.0,
        750.0,
        770.0,
        780.0,
        790.0,
        800.0,
        810.0,
        820.0,
        830.0,
        840.0,
        850.0,
        860.0,
        870.0,
        890.0,
        900.0,
        910.0,
        920.0,
        925.0,
        930.0,
        940.0,
        950.0,
        999.0,
        0.0,
        0.0,
        0.0,
        0.0,
        0.0,
        0.0,
        0.0,
        0.0,
        0.0,
        0.0,
        0.0,
        0.0,
        0.0,
        0.0,
        0.0,
        0.0,
        0.0,
        0.0,
        0.0,
        0.0,
        0.0,
        0.0,
        0.0,
        0.0,
        0.0,
        0.0,
        0.0
      ],
      "JSP": [
        "WP ",
        "WL ",
        "DF ",
        "GF ",
        "WH ",
        "RC ",
        "LP ",
        "ES ",
        "AF ",
        "PP ",
        "MH ",
        "WB ",
        "LM ",
        "LL ",
        "PM ",
        "RM ",
        "PY ",
        "AS ",
        "CO ",
        "MM ",
        "PB ",
        "OH ",
        "OS "
      ],
      "FIAJSP": [
        "119",
        "073",
        "202",
        "017",
        "263",
        "242",
        "108",
        "093",
        "019",
        "122",
        "264",
        "101",
        "113",
        "072",
        "133",
        "066",
        "231",
        "746",
        "740",
        "321",
        "375",
        "998",
        "299"
      ],
      "PLNJSP": [
        "PIMO3 ",
        "LAOC  ",
        "PSME  ",
        "ABGR  ",
        "TSHE  ",
        "THPL  ",
        "PICO  ",
        "PIEN  ",
        "ABLA  ",
        "PIPO  ",
        "TSME  ",
        "PIAL  ",
        "PIFL2 ",
        "LALY  ",
        "PIMO  ",
        "JUSC2 ",
        "TABR2 ",
        "POTR5 ",
        "POPUL ",
        "ACGL  ",
        "BEPA  ",
        "2TB   ",
        "2TN   "
      ],
      "NSP": [
        "WP1",
        "WL1",
        "DF1",
        "GF1",
        "WH1",
        "RC1",
        "LP1",
        "ES1",
        "AF1",
        "PP1",
        "MH1",
        "WB1",
        "LM1",
        "LL1",
        "PM1",
        "RM1",
        "PY1",
        "AS1",
        "CO1",
        "MM1",
        "PB1",
        "OH1",
        "OS1",
        "WP2",
        "WL2",
        "DF2",
        "GF2",
        "WH2",
        "RC2",
        "LP2",
        "ES2",
        "AF2",
        "PP2",
        "MH2",
        "WB2",
        "LM2",
        "LL2",
        "PM2",
        "RM2",
        "PY2",
        "AS2",
        "CO2",
        "MM2",
        "PB2",
        "OH2",
        "OS2",
        "WP3",
        "WL3",
        "DF3",
        "GF3",
        "WH3",
        "RC3",
        "LP3",
        "ES3",
        "AF3",
        "PP3",
        "MH3",
        "WB3",
        "LM3",
        "LL3",
        "PM3",
        "RM3",
        "PY3",
        "AS3",
        "CO3",
        "MM3",
        "PB3",
        "OH3",
        "OS3"
      ]
    },
    "other": {
      "YR": [
        10.0
      ],
      "IRECNT": [
        0.0
      ],
      "ICCODE": [
        0.0
      ],
      "JOTREE": [
        15.0,
        2.0,
        3.0,
        16.0,
        4.0,
        8.0
      ],
      "XMIN": [
        1.0,
        1.0,
        1.0,
        0.5,
        0.5,
        0.5,
        1.0,
        0.5,
        0.5,
        1.0,
        0.5,
        1.0,
        1.0,
        0.5,
        0.5,
        0.5,
        1.0,
        6.0,
        3.0,
        6.0,
        6.0,
        3.0,
        0.5
      ],
      "DBHMID": [
        1.0,
        3.0,
        5.0,
        7.0,
        9.0,
        12.0,
        16.0,
        20.0,
        24.0,
        28.0
      ],
      "ISPSPE": [
        17.0,
        18.0,
        19.0,
        20.0,
        21.0
      ],
      "BNORML": [
        1.0,
        1.0,
        1.0,
        1.046,
        1.093,
        1.139,
        1.186,
        1.232,
        1.278,
        1.325,
        1.371,
        1.418,
        1.464,
        1.51,
        1.557,
        1.603,
        1.649,
        1.696,
        1.742,
        1.789
      ],
      "HHTMAX": [
        23.0,
        27.0,
        21.0,
        21.0,
        22.0,
        20.0,
        24.0,
        18.0,
        18.0,
        17.0,
        22.0,
        27.0,
        27.0,
        18.0,
        6.0,
        6.0,
        27.0,
        16.0,
        16.0,
        16.0,
        16.0,
        16.0,
        22.0
      ],
      "IFORCD": [
        103.0,
        104.0,
        105.0,
        106.0,
        621.0,
        110.0,
        113.0,
        114.0,
        116.0,
        117.0,
        118.0,
        109.0,
        111.0,
        112.0,
        412.0,
        402.0,
        108.0,
        102.0,
        115.0,
        0.0
      ],
      "IFORST": [
        3.0,
        4.0,
        5.0,
        4.0,
        7.0,
        10.0,
        4.0,
        14.0,
        16.0,
        17.0,
        4.0,
        9.0,
        11.0,
        12.0,
        19.0,
        20.0,
        11.0,
        9.0,
        12.0,
        4.0
      ],
      "HT1": [
        5.19988,
        4.97407,
        4.81519,
        5.00233,
        4.97331,
        4.89564,
        4.62171,
        4.9219,
        4.76537,
        4.9288,
        4.77951,
        4.97407,
        4.192,
        4.76537,
        3.2,
        3.2,
        4.192,
        4.4421,
        4.4421,
        4.4421,
        4.4421,
        4.4421,
        4.77951
      ],
      "HT2": [
        -9.26718,
        -6.78347,
        -7.29306,
        -8.19365,
        -8.1973,
        -8.39057,
        -5.32481,
        -8.30289,
        -7.61062,
        -9.32795,
        -9.31743,
        -6.78347,
        -5.1651,
        -7.61062,
        -5.0,
        -5.0,
        -5.1651,
        -6.5405,
        -6.5405,
        -6.5405,
        -6.5405,
        -6.5405,
        -9.31743
      ],
      "SIGMAR": [
        0.3814,
        0.4243,
        0.4243,
        0.4166,
        0.4011,
        0.4125,
        0.3606,
        0.4121,
        0.4345,
        0.4243,
        0.3433,
        0.4243,
        0.4671,
        0.4345,
        0.2,
        0.2,
        0.4671,
        0.375,
        0.2,
        0.375,
        0.375,
        0.2,
        0.3433
      ],
      "REGNBK": [
        2.999
      ],
      "SS": [
        55329.0
      ],
      "JOSCRN": [
        6.0
      ],
      "JOSUME": [
        13.0
      ],
      "FSTOPEN": [
        27.0
      ],
      "MYACTS": [
        81.0
      ],
      "PARM": [
        0.0,
        -0.00204,
        0.0,
        -0.00183,
        0.0,
        0.0,
        0.0,
        -0.00203,
        -0.0019,
        -0.002165,
        -0.00264,
        -0.00204,
        0.0,
        -0.0019,
        0.0,
        0.0,
        0.0,
        0.0,
        0.0,
        0.0,
        0.0,
        0.0,
        -0.00264,
        0.0,
        0.0,
        0.0,
        0.0,
        -1.902e-06,
        0.0,
        0.0,
        0.0,
        0.0,
        0.0,
        0.0,
        0.0,
        0.0,
        0.0,
        0.0,
        0.0,
        0.0,
        0.0,
        0.0,
        0.0,
        0.0,
        0.0,
        0.0,
        -0.34566,
        0.0,
        0.0,
        0.0,
        0.0,
        0.17479,
        0.0,
        0.0,
        0.0,
        0.0,
        0.0,
        0.0,
        0.0,
        0.0,
        0.0,
        0.0,
        0.0,
        0.0,
        0.0,
        0.0,
        0.0,
        0.0,
        0.0,
        0.0,
        0.0,
        0.0,
        0.0,
        0.0,
        -0.00183,
        0.0,
        0.0,
        0.0,
        0.0,
        0.0,
        0.0,
        0.0,
        0.0,
        0.0,
        0.0,
        0.0,
        0.0,
        0.0,
        0.0,
        0.0,
        0.0,
        0.0,
        0.0,
        0.0,
        0.0,
        0.0,
        0.0,
        0.0,
        0.0,
        0.0,
        0.0,
        0.0,
        5.116e-06,
        0.0,
        0.0,
        0.0,
        0.0,
        0.0,
        0.0,
        0.0,
        0.0,
        0.0,
        0.0,
        0.0,
        5.116e-06,
        0.0,
        0.0,
        -0.15334,
        0.0,
        0.0,
        0.0,
        -0.18555,
        0.0,
        0.0,
        0.0,
        0.0,
        0.0,
        0.0,
        0.0,
        0.0,
        0.0,
        0.0,
        0.0,
        0.0,
        0.0,
        0.0,
        0.0,
        0.0,
        0.03882,
        0.0,
        0.0,
        0.0,
        0.03027,
        -0.0056,
        0.0,
        0.0,
        0.0,
        0.0,
        0.0,
        0.0,
        0.0,
        0.0,
        0.0,
        0.0,
        0.0,
        0.0,
        0.0,
        0.0,
        0.0,
        0.0,
        0.0,
        -0.0007,
        0.0,
        0.0,
        0.0,
        -0.00055,
        0.0,
        0.0,
        0.0,
        0.0,
        0.0,
        0.0,
        0.0,
        0.0,
        0.0,
        0.0,
        0.0,
        0.0,
        0.0,
        0.0,
        0.0,
        0.0,
        0.0,
        0.0,
        0.0,
        0.30066,
        0.3384,
        0.24293,
        0.0,
        0.0,
        0.53172,
        0.29699,
        0.23372,
        0.26558,
        0.0,
        0.30066,
        0.0,
        0.23372,
        0.0,
        0.0,
        0.0,
        0.0,
        0.0,
        0.0,
        0.0,
        0.0,
        0.0,
        0.0,
        0.0,
        0.0,
        0.0,
        0.0,
        0.0,
        -0.02989,
        0.0,
        0.0,
        0.0,
        0.0,
        0.0,
        0.0,
        0.0,
        0.0,
        0.0,
        0.0,
        0.0,
        0.0,
        0.0,
        0.0,
        0.0,
        0.0,
        0.0,
        0.0,
        0.0,
        0.0,
        0.0,
        0.0,
        0.00011,
        0.0,
        0.0,
        0.0,
        0.0,
        0.0,
        0.0,
        0.0,
        0.0,
        0.0,
        0.0,
        0.0,
        0.0,
        0.0,
        0.0,
        0.0,
        0.0,
        -0.21217,
        -0.59302,
        -0.59685,
        -0.25601,
        -0.25776,
        0.0,
        0.0,
        -0.38334,
        -0.28433,
        -0.31555,
        -0.25138,
        -0.59302,
        0.0,
        -0.28433,
        0.0,
        0.0,
        0.0,
        0.0,
        0.0,
        0.0,
        0.0,
        0.0,
        -0.25138,
        0.00301,
        0.0,
        0.0,
        0.0,
        0.0,
        0.0,
        0.0042,
        0.0,
        0.001903,
        0.0,
        0.0,
        0.0,
        0.0,
        0.001903,
        0.0,
        0.0,
        0.0,
        0.0,
        0.0,
        0.0,
        0.0,
        0.0,
        0.0,
        0.0,
        0.19558,
        0.16488,
        0.0726,
        0.06887,
        0.1105,
        0.0,
        0.09918,
        0.0,
        0.16072,
        0.0514,
        0.19558,
        0.0,
        0.0,
        0.0,
        0.0,
        0.0,
        0.0,
        0.0,
        0.0,
        0.0,
        0.0,
        0.0514
      ],
      "CRHAB": [
        0.8884,
        0.7309,
        0.9347,
        0.9888,
        0.9945,
        1.1126,
        1.0263,
        0.0,
        0.0,
        0.0,
        0.0,
        0.0,
        0.0,
        0.0,
        0.06533,
        0.03441,
        0.2307,
        0.1661,
        -0.1253,
        -0.05018,
        0.11005,
        0.08113,
        0.1782,
        0.03919,
        0.2107,
        0.0,
        0.0,
        0.0,
        0.8643,
        0.7271,
        0.984,
        0.8127,
        0.8874,
        0.7055,
        0.7708,
        0.7849,
        0.8038,
        0.8742,
        0.8232,
        0.8415,
        0.9759,
        0.0,
        -0.2304,
        -0.5421,
        -0.4343,
        -0.3759,
        -0.4129,
        -0.4879,
        -0.2674,
        -0.1941,
        0.0,
        0.0,
        0.0,
        0.0,
        0.0,
        0.0,
        -0.2413,
        0.0,
        0.0,
        0.0,
        0.0,
        0.0,
        0.0,
        0.0,
        0.0,
        0.0,
        0.0,
        0.0,
        0.0,
        0.0,
        -1.6053,
        -1.7128,
        0.0,
        0.0,
        0.0,
        0.0,
        0.0,
        0.0,
        0.0,
        0.0,
        0.0,
        0.0,
        0.0,
        0.0,
        -0.3785,
        -0.4142,
        -0.3985,
        -0.2987,
        -0.381,
        -0.4087,
        -0.3577,
        -0.2994,
        -0.2486,
        -0.2863,
        -0.1968,
        -0.4931,
        -0.2676,
        -0.5625,
        0.05351,
        -0.05031,
        0.1075,
        -0.1872,
        0.01729,
        0.03667,
        0.01885,
        0.09102,
        0.1371,
        0.08368,
        0.123,
        -0.02365,
        0.0,
        0.0,
        0.09453,
        -0.0774,
        0.07113,
        0.2039,
        0.06176,
        0.1513,
        0.09086,
        0.158,
        0.09229,
        0.01551,
        0.0,
        0.0,
        0.0,
        0.0,
        -0.9436,
        -0.8654,
        -0.8849,
        -0.9067,
        -0.8783,
        -1.0103,
        -1.0268,
        -1.005,
        -1.0301,
        0.0,
        0.0,
        0.0,
        0.0,
        0.0,
        0.4649,
        0.3211,
        0.197,
        0.2295,
        0.3383,
        0.345,
        0.0,
        0.0,
        0.0,
        0.0,
        0.0,
        0.0,
        0.0,
        0.0,
        0.06533,
        0.03441,
        0.2307,
        0.1661,
        -0.1253,
        -0.05018,
        0.11005,
        0.1782,
        0.03919,
        0.2107,
        0.0,
        0.0,
        0.0,
        0.0,
        0.0,
        0.0,
        0.0,
        0.0,
        0.0,
        0.0,
        0.0,
        0.0,
        0.0,
        0.0,
        0.0,
        0.0,
        0.0,
        0.09453,
        -0.0774,
        0.07113,
        0.2039,
        0.06176,
        0.1513,
        0.09086,
        0.158,
        0.09229,
        0.01551,
        0.0,
        0.0,
        0.0,
        0.0,
        0.0,
        0.0,
        0.0,
        0.0,
        0.0,
        0.0,
        0.0,
        0.0,
        0.0,
        0.0,
        0.0,
        0.0,
        0.0,
        0.0,
        0.0,
        0.0,
        0.0,
        0.0,
        0.0,
        0.0,
        0.0,
        0.0,
        0.0,
        0.0,
        0.0,
        0.0,
        0.0,
        0.0,
        0.0,
        0.0,
        0.0,
        0.0,
        0.0,
        0.0,
        0.0,
        0.0,
        0.0,
        0.0,
        0.0,
        0.0,
        0.0,
        0.0,
        0.0,
        0.0,
        0.0,
        0.0,
        0.0,
        0.0,
        0.0,
        0.0,
        0.0,
        0.0,
        0.0,
        0.0,
        0.0,
        0.0,
        0.0,
        0.0,
        0.0,
        0.0,
        0.0,
        0.0,
        0.0,
        0.0,
        0.0,
        0.0,
        0.0,
        0.0,
        0.0,
        0.0,
        0.0,
        0.0,
        0.0,
        0.0,
        0.0,
        0.0,
        0.0,
        0.0,
        0.0,
        0.0,
        0.0,
        0.0,
        0.0,
        0.0,
        0.0,
        0.0,
        0.0,
        0.0,
        0.0,
        0.0,
        0.0,
        0.0,
        0.0,
        0.0,
        0.0,
        0.0,
        0.0,
        0.0,
        0.0,
        0.0,
        0.0,
        0.0,
        0.0,
        0.0,
        0.0,
        0.0,
        0.0,
        0.0,
        0.0,
        0.0,
        0.0,
        0.0,
        0.4649,
        0.3211,
        0.197,
        0.2295,
        0.3383,
        0.345,
        0.0,
        0.0,
        0.0,
        0.0,
        0.0,
        0.0,
        0.0,
        0.0
      ],
      "CRSD": [
        6.35
      ],
      "WEIBA": [
        0.0,
        0.0,
        0.0,
        0.0,
        0.0,
        0.0,
        0.0,
        0.0,
        0.0,
        0.0,
        0.0,
        0.0,
        1.0,
        0.0,
        0.0,
        0.0,
        1.0,
        0.0,
        0.0,
        0.0,
        0.0,
        0.0,
        0.0
      ],
      "WEIBB0": [
        0.0,
        0.0,
        0.0,
        0.0,
        0.0,
        0.0,
        0.0,
        0.0,
        0.0,
        0.0,
        0.0,
        0.0,
        -0.82631,
        0.0,
        0.0,
        0.0,
        -0.82631,
        -0.08414,
        0.0,
        -0.08414,
        -0.08414,
        0.0,
        0.0
      ],
      "WEIBC0": [
        0.0,
        0.0,
        0.0,
        0.0,
        0.0,
        0.0,
        0.0,
        0.0,
        0.0,
        0.0,
        0.0,
        0.0,
        3.31429,
        0.0,
        0.0,
        0.0,
        3.31429,
        2.775,
        0.0,
        2.775,
        2.775,
        0.0,
        0.0
      ],
      "WEIBC1": [
        0.0,
        0.0,
        0.0,
        0.0,
        0.0,
        0.0,
        0.0,
        0.0,
        0.0,
        0.0,
        0.0,
        0.0,
        0.0,
        0.0,
        0.0,
        0.0,
        0.0,
        0.0,
        0.0,
        0.0,
        0.0,
        0.0,
        0.0
      ],
      "C0": [
        0.0,
        0.0,
        0.0,
        0.0,
        0.0,
        0.0,
        0.0,
        0.0,
        0.0,
        0.0,
        0.0,
        0.0,
        6.19911,
        0.0,
        0.0,
        0.0,
        6.19911,
        4.01678,
        0.0,
        4.01678,
        4.01678,
        0.0,
        0.0
      ],
      "C1": [
        0.0,
        0.0,
        0.0,
        0.0,
        0.0,
        0.0,
        0.0,
        0.0,
        0.0,
        0.0,
        0.0,
        0.0,
        -0.02216,
        0.0,
        0.0,
        0.0,
        -0.02216,
        -0.01516,
        0.0,
        -0.01516,
        -0.01516,
        0.0,
        0.0
      ],
      "DGLD": [
        0.56445,
        0.5414,
        0.56888,
        0.6881,
        0.68712,
        0.58705,
        0.89503,
        0.73045,
        0.8624,
        0.66101,
        0.89778,
        0.5414,
        0.213947,
        0.8624,
        0.0,
        0.0,
        0.213947,
        0.0,
        0.0,
        0.0,
        0.0,
        0.0,
        0.89778
      ],
      "DGCR": [
        1.08338,
        1.03478,
        2.0685,
        1.93969,
        1.64133,
        1.2936,
        1.85558,
        1.54643,
        0.52044,
        1.31618,
        1.28403,
        1.03478,
        1.523464,
        0.52044,
        0.0,
        0.0,
        1.523464,
        0.0,
        0.0,
        0.0,
        0.0,
        0.0,
        1.28403
      ],
      "DGCRSQ": [
        0.0,
        0.07509,
        -0.62361,
        -0.78258,
        -0.27244,
        0.0,
        -0.36393,
        -0.26635,
        0.86236,
        0.0,
        0.0,
        0.07509,
        0.0,
        0.86236,
        0.0,
        0.0,
        0.0,
        0.0,
        0.0,
        0.0,
        0.0,
        0.0,
        0.0
      ],
      "DGBAL": [
        0.42112,
        0.43637,
        0.50202,
        0.45142,
        0.0,
        0.74596,
        -0.03665,
        0.25639,
        0.0,
        0.0,
        0.0,
        0.43637,
        -0.358634,
        0.0,
        0.0,
        0.0,
        -0.358634,
        0.0,
        0.0,
        0.0,
        0.0,
        0.0,
        0.0
      ],
      "DGDBAL": [
        -2.08272,
        -2.03256,
        -2.1159,
        -1.76812,
        -0.80918,
        -2.28375,
        -0.43329,
        -1.18218,
        -0.5127,
        -1.25881,
        -0.6611,
        -2.03256,
        0.0,
        -0.5127,
        0.0,
        0.0,
        0.0,
        0.0,
        0.0,
        0.0,
        0.0,
        0.0,
        -0.6611
      ],
      "OBSERV": [
        1635.0,
        76.0,
        94.0,
        0.0,
        0.0,
        0.0,
        968.0,
        900.0,
        797.0,
        1124.0,
        47.0,
        809.0,
        1079.0,
        1682.0,
        4014.0,
        63.0,
        4684.0,
        0.0,
        816.0,
        67.0,
        122.0,
        3678.0,
        0.0,
        0.0,
        1774.0,
        0.0,
        0.0,
        0.0,
        0.0,
        0.0,
        1176.0,
        67.0,
        1198.0,
        0.0,
        0.0,
        0.0,
        93.0,
        940.0,
        62.0,
        2548.0,
        719.0,
        2590.0,
        907.0,
        827.0,
        46.0,
        35.0,
        146.0,
        3092.0,
        988.0,
        177.0,
        40.0,
        331.0,
        332.0,
        2380.0,
        429.0,
        59.0,
        605.0,
        17.0,
        879.0,
        0.0,
        55.0,
        880.0,
        0.0,
        0.0,
        0.0,
        0.0,
        968.0,
        900.0,
        797.0,
        1124.0,
        47.0,
        809.0,
        27.0,
        70.0,
        123.0,
        101.0,
        33.0,
        0.0,
        988.0,
        177.0,
        40.0,
        331.0,
        332.0,
        2380.0,
        1000.0,
        1000.0,
        1000.0,
        1000.0,
        1000.0,
        1000.0,
        1000.0,
        1000.0,
        1000.0,
        1000.0,
        1000.0,
        1000.0,
        27.0,
        70.0,
        123.0,
        101.0,
        33.0,
        0.0,
        184.0,
        429.0,
        356.0,
        162.0,
        74.0,
        0.0,
        1000.0,
        1000.0,
        1000.0,
        1000.0,
        1000.0,
        1000.0,
        184.0,
        429.0,
        356.0,
        162.0,
        74.0,
        0.0,
        184.0,
        429.0,
        356.0,
        162.0,
        74.0,
        0.0,
        1000.0,
        1000.0,
        1000.0,
        1000.0,
        1000.0,
        1000.0,
        55.0,
        880.0,
        0.0,
        0.0,
        0.0,
        0.0
      ],
      "MAPHAB": [
        1.0,
        1.0,
        2.0,
        2.0,
        2.0,
        2.0,
        2.0,
        2.0,
        2.0,
        3.0,
        3.0,
        4.0,
        5.0,
        6.0,
        7.0,
        7.0,
        7.0,
        7.0,
        4.0,
        4.0,
        1.0,
        4.0,
        4.0,
        8.0,
        8.0,
        8.0,
        1.0,
        1.0,
        1.0,
        1.0
      ],
      "DGHAB": [
        1.15584,
        1.05635,
        0.0,
        0.0,
        0.0,
        0.0,
        0.38335,
        0.51291,
        0.45377,
        0.71322,
        0.26835,
        0.0,
        0.4778,
        0.15228,
        0.29764,
        0.0,
        0.0,
        0.0,
        0.66755,
        0.60454,
        0.0,
        0.0,
        0.0,
        0.0,
        0.45264,
        0.0,
        0.0,
        0.0,
        0.0,
        0.0,
        1.61452,
        1.31772,
        0.0,
        0.0,
        0.0,
        0.0,
        0.77399,
        0.67828,
        0.64451,
        0.37945,
        0.54337,
        0.0,
        -0.58842,
        -0.21235,
        -0.71629,
        -0.53954,
        0.0,
        0.0,
        -0.96389,
        -0.72415,
        -0.57308,
        -0.82218,
        -1.24093,
        -1.10746,
        1.16233,
        0.73408,
        0.51417,
        0.0,
        0.0,
        0.0,
        -1.68033,
        -1.52111,
        0.0,
        0.0,
        0.0,
        0.0,
        0.38335,
        0.51291,
        0.45377,
        0.71322,
        0.26835,
        0.0,
        0.0,
        0.0,
        0.0,
        0.0,
        0.0,
        0.0,
        -0.96389,
        -0.72415,
        -0.57308,
        -0.82218,
        -1.24093,
        -1.10746,
        0.0,
        0.0,
        0.0,
        0.0,
        0.0,
        0.0,
        0.0,
        0.0,
        0.0,
        0.0,
        0.0,
        0.0,
        0.0,
        0.0,
        0.0,
        0.0,
        0.0,
        0.0,
        0.0,
        0.0,
        0.0,
        0.0,
        0.0,
        0.0,
        0.0,
        0.0,
        0.0,
        0.0,
        0.0,
        0.0,
        0.0,
        0.0,
        0.0,
        0.0,
        0.0,
        0.0,
        0.0,
        0.0,
        0.0,
        0.0,
        0.0,
        0.0,
        0.0,
        0.0,
        0.0,
        0.0,
        0.0,
        0.0,
        -1.68033,
        -1.52111,
        0.0,
        0.0,
        0.0,
        0.0
      ],
      "MAPCCF": [
        3.0,
        3.0,
        3.0,
        3.0,
        3.0,
        3.0,
        3.0,
        3.0,
        3.0,
        3.0,
        3.0,
        3.0,
        1.0,
        3.0,
        3.0,
        3.0,
        1.0,
        3.0,
        3.0,
        3.0,
        3.0,
        2.0,
        2.0,
        3.0,
        3.0,
        3.0,
        3.0,
        3.0,
        3.0,
        3.0,
        3.0,
        3.0,
        3.0,
        3.0,
        3.0,
        3.0,
        3.0,
        3.0,
        3.0,
        3.0,
        3.0,
        1.0,
        3.0,
        3.0,
        3.0,
        3.0,
        3.0,
        3.0,
        2.0,
        3.0,
        1.0,
        3.0,
        3.0,
        1.0,
        3.0,
        3.0,
        3.0,
        3.0,
        3.0,
        3.0,
        4.0,
        4.0,
        4.0,
        4.0,
        4.0,
        4.0,
        1.0,
        2.0,
        4.0,
        4.0,
        4.0,
        2.0,
        1.0,
        4.0,
        4.0,
        4.0,
        3.0,
        4.0,
        4.0,
        4.0,
        1.0,
        3.0,
        2.0,
        4.0,
        4.0,
        4.0,
        4.0,
        2.0,
        4.0,
        4.0,
        3.0,
        3.0,
        3.0,
        3.0,
        3.0,
        3.0,
        3.0,
        3.0,
        3.0,
        3.0,
        3.0,
        3.0,
        1.0,
        3.0,
        3.0,
        3.0,
        3.0,
        3.0,
        3.0,
        3.0,
        3.0,
        3.0,
        2.0,
        2.0,
        3.0,
        3.0,
        3.0,
        3.0,
        3.0,
        3.0,
        1.0,
        1.0,
        1.0,
        1.0,
        1.0,
        1.0,
        1.0,
        1.0,
        1.0,
        1.0,
        1.0,
        1.0,
        1.0,
        1.0,
        1.0,
        1.0,
        1.0,
        1.0,
        1.0,
        1.0,
        1.0,
        1.0,
        1.0,
        1.0,
        1.0,
        1.0,
        1.0,
        1.0,
        1.0,
        1.0,
        3.0,
        3.0,
        3.0,
        3.0,
        3.0,
        3.0,
        3.0,
        3.0,
        3.0,
        3.0,
        3.0,
        3.0,
        3.0,
        1.0,
        2.0,
        2.0,
        3.0,
        3.0,
        2.0,
        3.0,
        3.0,
        1.0,
        3.0,
        3.0,
        3.0,
        3.0,
        3.0,
        3.0,
        3.0,
        3.0,
        4.0,
        4.0,
        1.0,
        4.0,
        3.0,
        4.0,
        2.0,
        1.0,
        4.0,
        1.0,
        4.0,
        4.0,
        4.0,
        2.0,
        2.0,
        2.0,
        2.0,
        2.0,
        2.0,
        4.0,
        1.0,
        4.0,
        1.0,
        4.0,
        4.0,
        4.0,
        1.0,
        4.0,
        4.0,
        4.0,
        4.0,
        4.0,
        4.0,
        4.0,
        4.0,
        4.0,
        4.0,
        4.0,
        4.0,
        4.0,
        4.0,
        3.0,
        3.0,
        1.0,
        1.0,
        1.0,
        3.0,
        3.0,
        1.0,
        4.0,
        2.0,
        4.0,
        1.0,
        4.0,
        4.0,
        4.0,
        1.0,
        4.0,
        4.0,
        4.0,
        3.0,
        3.0,
        3.0,
        3.0,
        3.0,
        3.0,
        3.0,
        3.0,
        3.0,
        3.0,
        3.0,
        3.0,
        1.0,
        1.0,
        1.0,
        1.0,
        1.0,
        1.0,
        1.0,
        3.0,
        1.0,
        1.0,
        2.0,
        2.0,
        1.0,
        3.0,
        1.0,
        1.0,
        3.0,
        3.0,
        2.0,
        2.0,
        3.0,
        1.0,
        4.0,
        3.0,
        3.0,
        1.0,
        2.0,
        4.0,
        4.0,
        1.0,
        4.0,
        4.0,
        4.0,
        4.0,
        1.0,
        4.0,
        4.0,
        4.0,
        4.0,
        4.0,
        4.0,
        4.0,
        4.0,
        4.0,
        4.0,
        4.0,
        4.0,
        4.0,
        1.0,
        1.0,
        1.0,
        1.0,
        1.0,
        1.0,
        1.0,
        1.0,
        1.0,
        1.0,
        1.0,
        1.0,
        1.0,
        1.0,
        1.0,
        1.0,
        1.0,
        1.0,
        1.0,
        1.0,
        1.0,
        1.0,
        1.0,
        1.0,
        1.0,
        1.0,
        1.0,
        1.0,
        1.0,
        1.0,
        3.0,
        3.0,
        3.0,
        3.0,
        3.0,
        3.0,
        3.0,
        3.0,
        3.0,
        3.0,
        3.0,
        1.0,
        3.0,
        3.0,
        3.0,
        3.0,
        3.0,
        3.0,
        2.0,
        3.0,
        1.0,
        3.0,
        3.0,
        1.0,
        3.0,
        3.0,
        3.0,
        3.0,
        3.0,
        3.0,
        1.0,
        1.0,
        1.0,
        1.0,
        1.0,
        1.0,
        1.0,
        1.0,
        1.0,
        1.0,
        1.0,
        1.0,
        1.0,
        1.0,
        1.0,
        1.0,
        1.0,
        1.0,
        1.0,
        1.0,
        1.0,
        1.0,
        1.0,
        1.0,
        1.0,
        1.0,
        1.0,
        1.0,
        1.0,
        1.0,
        3.0,
        3.0,
        3.0,
        3.0,
        3.0,
        3.0,
        3.0,
        3.0,
        3.0,
        3.0,
        3.0,
        3.0,
        1.0,
        1.0,
        1.0,
        1.0,
        1.0,
        1.0,
        1.0,
        3.0,
        1.0,
        1.0,
        2.0,
        2.0,
        1.0,
        3.0,
        1.0,
        1.0,
        3.0,
        3.0,
        1.0,
        1.0,
        1.0,
        1.0,
        1.0,
        1.0,
        1.0,
        1.0,
        1.0,
        1.0,
        1.0,
        1.0,
        1.0,
        1.0,
        1.0,
        1.0,
        1.0,
        1.0,
        1.0,
        1.0,
        1.0,
        1.0,
        1.0,
        1.0,
        1.0,
        1.0,
        1.0,
        1.0,
        1.0,
        1.0,
        1.0,
        1.0,
        1.0,
        1.0,
        1.0,
        1.0,
        1.0,
        1.0,
        1.0,
        1.0,
        1.0,
        1.0,
        1.0,
        1.0,
        1.0,
        1.0,
        1.0,
        1.0,
        1.0,
        1.0,
        1.0,
        1.0,
        1.0,
        1.0,
        1.0,
        1.0,
        1.0,
        1.0,
        1.0,
        1.0,
        1.0,
        1.0,
        1.0,
        1.0,
        1.0,
        1.0,
        1.0,
        1.0,
        1.0,
        1.0,
        1.0,
        1.0,
        1.0,
        1.0,
        1.0,
        1.0,
        1.0,
        1.0,
        1.0,
        1.0,
        1.0,
        1.0,
        1.0,
        1.0,
        1.0,
        1.0,
        1.0,
        1.0,
        1.0,
        1.0,
        1.0,
        1.0,
        1.0,
        1.0,
        1.0,
        1.0,
        1.0,
        1.0,
        1.0,
        1.0,
        1.0,
        1.0,
        1.0,
        1.0,
        1.0,
        1.0,
        1.0,
        1.0,
        1.0,
        1.0,
        1.0,
        1.0,
        1.0,
        1.0,
        1.0,
        1.0,
        1.0,
        1.0,
        1.0,
        1.0,
        1.0,
        1.0,
        1.0,
        1.0,
        1.0,
        1.0,
        1.0,
        1.0,
        1.0,
        1.0,
        1.0,
        1.0,
        1.0,
        1.0,
        1.0,
        1.0,
        1.0,
        1.0,
        1.0,
        1.0,
        1.0,
        1.0,
        1.0,
        1.0,
        1.0,
        1.0,
        1.0,
        1.0,
        1.0,
        1.0,
        1.0,
        1.0,
        1.0,
        1.0,
        1.0,
        1.0,
        1.0,
        1.0,
        1.0,
        1.0,
        1.0,
        1.0,
        1.0,
        1.0,
        1.0,
        1.0,
        1.0,
        1.0,
        1.0,
        1.0,
        1.0,
        1.0,
        1.0,
        1.0,
        1.0,
        1.0,
        1.0,
        1.0,
        1.0,
        1.0,
        1.0,
        1.0,
        1.0,
        1.0,
        1.0,
        1.0,
        1.0,
        1.0,
        1.0,
        1.0,
        1.0,
        1.0,
        1.0,
        1.0,
        1.0,
        1.0,
        1.0,
        1.0,
        1.0,
        1.0,
        1.0,
        1.0,
        1.0,
        1.0,
        1.0,
        1.0,
        1.0,
        1.0,
        1.0,
        1.0,
        1.0,
        1.0,
        1.0,
        1.0,
        1.0,
        1.0,
        1.0,
        1.0,
        1.0,
        1.0,
        1.0,
        1.0,
        1.0,
        1.0,
        1.0,
        1.0,
        1.0,
        1.0,
        1.0,
        1.0,
        1.0,
        1.0,
        1.0,
        1.0,
        1.0,
        1.0,
        1.0,
        1.0,
        1.0,
        1.0,
        1.0,
        1.0,
        1.0,
        1.0,
        1.0,
        1.0,
        1.0,
        1.0,
        1.0,
        1.0,
        1.0,
        1.0,
        1.0,
        1.0,
        1.0,
        1.0,
        1.0,
        1.0,
        1.0,
        1.0,
        1.0,
        1.0,
        1.0,
        1.0,
        1.0,
        1.0,
        1.0,
        1.0,
        1.0,
        1.0
      ],
      "DGCCFA": [
        -0.0243,
        -0.24886,
        -0.01079,
        0.0,
        0.0,
        -0.10144,
        -0.14793,
        -0.05438,
        0.0,
        0.0,
        -0.09046,
        -0.11884,
        -0.05529,
        -0.0218,
        0.0,
        -0.09624,
        -0.19544,
        -0.05119,
        0.0,
        0.0,
        0.0,
        0.0,
        0.0,
        0.0,
        0.0,
        -0.05054,
        -0.15356,
        -0.09396,
        0.0,
        0.0,
        -0.05576,
        -0.14919,
        -0.4064,
        -0.114,
        0.0,
        -0.01547,
        -0.38386,
        -0.05371,
        -0.15159,
        0.0,
        -0.01598,
        -0.04477,
        -0.07392,
        0.0,
        0.0,
        -0.10416,
        -0.88809,
        -0.25938,
        -0.14726,
        0.0,
        -0.10744,
        0.0,
        0.0,
        0.0,
        0.0,
        -0.10144,
        -0.14793,
        -0.05438,
        0.0,
        0.0,
        -0.199592,
        0.0,
        0.0,
        0.0,
        0.0,
        -0.01598,
        -0.04477,
        -0.07392,
        0.0,
        0.0,
        0.0,
        0.0,
        0.0,
        0.0,
        0.0,
        0.0,
        0.0,
        0.0,
        0.0,
        0.0,
        -0.199592,
        0.0,
        0.0,
        0.0,
        0.0,
        0.0,
        0.0,
        0.0,
        0.0,
        0.0,
        0.0,
        0.0,
        0.0,
        0.0,
        0.0,
        0.0,
        0.0,
        0.0,
        0.0,
        0.0,
        0.0,
        0.0,
        0.0,
        0.0,
        0.0,
        0.0,
        0.0,
        0.0,
        0.0,
        0.0,
        -0.10744,
        0.0,
        0.0,
        0.0,
        0.0
      ],
      "MAPLOC": [
        2.0,
        1.0,
        2.0,
        2.0,
        2.0,
        2.0,
        2.0,
        2.0,
        2.0,
        2.0,
        1.0,
        1.0,
        1.0,
        1.0,
        2.0,
        3.0,
        3.0,
        2.0,
        5.0,
        5.0,
        4.0,
        1.0,
        5.0,
        4.0,
        1.0,
        2.0,
        3.0,
        3.0,
        2.0,
        3.0,
        5.0,
        1.0,
        4.0,
        6.0,
        5.0,
        1.0,
        2.0,
        2.0,
        3.0,
        2.0,
        4.0,
        6.0,
        2.0,
        5.0,
        3.0,
        2.0,
        3.0,
        1.0,
        3.0,
        3.0,
        3.0,
        3.0,
        3.0,
        3.0,
        2.0,
        4.0,
        1.0,
        1.0,
        1.0,
        2.0,
        2.0,
        3.0,
        4.0,
        2.0,
        1.0,
        1.0,
        4.0,
        2.0,
        1.0,
        1.0,
        2.0,
        4.0,
        3.0,
        3.0,
        4.0,
        2.0,
        2.0,
        3.0,
        1.0,
        1.0,
        1.0,
        3.0,
        2.0,
        3.0,
        3.0,
        3.0,
        1.0,
        1.0,
        4.0,
        1.0,
        1.0,
        2.0,
        2.0,
        3.0,
        3.0,
        4.0,
        4.0,
        2.0,
        1.0,
        1.0,
        2.0,
        2.0,
        2.0,
        1.0,
        4.0,
        3.0,
        1.0,
        4.0,
        3.0,
        2.0,
        3.0,
        2.0,
        1.0,
        1.0,
        3.0,
        3.0,
        3.0,
        3.0,
        1.0,
        3.0,
        2.0,
        1.0,
        1.0,
        1.0,
        2.0,
        3.0,
        3.0,
        2.0,
        5.0,
        5.0,
        4.0,
        1.0,
        1.0,
        1.0,
        1.0,
        1.0,
        1.0,
        1.0,
        1.0,
        1.0,
        1.0,
        1.0,
        1.0,
        4.0,
        1.0,
        1.0,
        2.0,
        2.0,
        3.0,
        3.0,
        4.0,
        4.0,
        2.0,
        1.0,
        1.0,
        1.0,
        1.0,
        1.0,
        1.0,
        1.0,
        1.0,
        1.0,
        1.0,
        1.0,
        1.0,
        1.0,
        1.0,
        1.0,
        1.0,
        1.0,
        1.0,
        1.0,
        1.0,
        1.0,
        1.0,
        1.0,
        1.0,
        1.0,
        1.0,
        1.0,
        1.0,
        1.0,
        1.0,
        1.0,
        1.0,
        1.0,
        1.0,
        1.0,
        1.0,
        1.0,
        1.0,
        1.0,
        1.0,
        1.0,
        1.0,
        1.0,
        1.0,
        1.0,
        1.0,
        1.0,
        1.0,
        1.0,
        1.0,
        1.0,
        1.0,
        1.0,
        1.0,
        1.0,
        1.0,
        1.0,
        1.0,
        1.0,
        1.0,
        1.0,
        1.0,
        1.0,
        1.0,
        1.0,
        1.0,
        1.0,
        1.0,
        1.0,
        1.0,
        1.0,
        1.0,
        1.0,
        1.0,
        1.0,
        1.0,
        1.0,
        1.0,
        1.0,
        1.0,
        1.0,
        1.0,
        1.0,
        1.0,
        1.0,
        1.0,
        1.0,
        1.0,
        1.0,
        3.0,
        2.0,
        1.0,
        1.0,
        3.0,
        3.0,
        3.0,
        3.0,
        1.0,
        3.0,
        2.0
      ],
      "DGFOR": [
        0.1692,
        0.0,
        0.0,
        0.0,
        0.0,
        0.0,
        0.20004,
        0.07656,
        0.08188,
        0.30379,
        0.0,
        0.0,
        0.50357,
        0.3492,
        0.21961,
        0.61812,
        0.0,
        0.0,
        0.43443,
        0.28344,
        -0.14829,
        0.20205,
        0.57763,
        0.0,
        0.10667,
        0.44357,
        0.0,
        0.0,
        0.0,
        0.0,
        0.5007,
        0.17647,
        0.31745,
        0.0,
        0.0,
        0.0,
        0.43735,
        0.21113,
        0.14808,
        0.0,
        0.0,
        0.0,
        0.26262,
        -0.15871,
        0.0,
        0.0,
        0.0,
        0.0,
        0.42062,
        0.14072,
        -0.13001,
        0.0,
        0.0,
        0.0,
        0.24588,
        0.56958,
        0.42787,
        0.0,
        0.0,
        0.0,
        0.1252,
        0.48076,
        0.0,
        0.0,
        0.0,
        0.0,
        0.20004,
        0.07656,
        0.08188,
        0.30379,
        0.0,
        0.0,
        1.568742,
        0.0,
        0.0,
        0.0,
        0.0,
        0.0,
        0.42062,
        0.14072,
        -0.13001,
        0.0,
        0.0,
        0.0,
        0.0,
        0.0,
        0.0,
        0.0,
        0.0,
        0.0,
        0.0,
        0.0,
        0.0,
        0.0,
        0.0,
        0.0,
        1.568742,
        0.0,
        0.0,
        0.0,
        0.0,
        0.0,
        0.0,
        0.0,
        0.0,
        0.0,
        0.0,
        0.0,
        0.0,
        0.0,
        0.0,
        0.0,
        0.0,
        0.0,
        0.0,
        0.0,
        0.0,
        0.0,
        0.0,
        0.0,
        0.0,
        0.0,
        0.0,
        0.0,
        0.0,
        0.0,
        0.0,
        0.0,
        0.0,
        0.0,
        0.0,
        0.0,
        0.1252,
        0.48076,
        0.0,
        0.0,
        0.0,
        0.0
      ],
      "MAPDSQ": [
        1.0,
        2.0,
        2.0,
        2.0,
        2.0,
        1.0,
        2.0,
        1.0,
        1.0,
        1.0,
        2.0,
        1.0,
        2.0,
        1.0,
        1.0,
        1.0,
        1.0,
        1.0,
        1.0,
        1.0,
        1.0,
        2.0,
        1.0,
        4.0,
        2.0,
        2.0,
        2.0,
        3.0,
        1.0,
        4.0,
        1.0,
        1.0,
        4.0,
        1.0,
        1.0,
        1.0,
        1.0,
        1.0,
        2.0,
        2.0,
        3.0,
        1.0,
        2.0,
        1.0,
        1.0,
        3.0,
        1.0,
        2.0,
        3.0,
        1.0,
        1.0,
        1.0,
        1.0,
        1.0,
        3.0,
        1.0,
        1.0,
        2.0,
        1.0,
        1.0,
        1.0,
        1.0,
        2.0,
        1.0,
        2.0,
        1.0,
        1.0,
        1.0,
        2.0,
        2.0,
        1.0,
        1.0,
        2.0,
        3.0,
        1.0,
        4.0,
        1.0,
        1.0,
        1.0,
        2.0,
        1.0,
        1.0,
        1.0,
        3.0,
        2.0,
        1.0,
        1.0,
        1.0,
        1.0,
        2.0,
        2.0,
        1.0,
        2.0,
        1.0,
        1.0,
        2.0,
        1.0,
        1.0,
        2.0,
        1.0,
        2.0,
        2.0,
        2.0,
        2.0,
        3.0,
        3.0,
        2.0,
        1.0,
        1.0,
        2.0,
        1.0,
        2.0,
        1.0,
        1.0,
        1.0,
        1.0,
        1.0,
        1.0,
        2.0,
        1.0,
        2.0,
        1.0,
        2.0,
        1.0,
        1.0,
        1.0,
        1.0,
        1.0,
        1.0,
        1.0,
        1.0,
        2.0,
        1.0,
        1.0,
        1.0,
        1.0,
        1.0,
        1.0,
        1.0,
        1.0,
        1.0,
        1.0,
        1.0,
        1.0,
        2.0,
        2.0,
        1.0,
        2.0,
        1.0,
        1.0,
        2.0,
        1.0,
        1.0,
        2.0,
        1.0,
        1.0,
        1.0,
        1.0,
        1.0,
        1.0,
        1.0,
        1.0,
        1.0,
        1.0,
        1.0,
        1.0,
        1.0,
        1.0,
        1.0,
        1.0,
        1.0,
        1.0,
        1.0,
        1.0,
        1.0,
        1.0,
        1.0,
        1.0,
        1.0,
        1.0,
        1.0,
        1.0,
        1.0,
        1.0,
        1.0,
        1.0,
        1.0,
        1.0,
        1.0,
        1.0,
        1.0,
        1.0,
        1.0,
        1.0,
        1.0,
        1.0,
        1.0,
        1.0,
        1.0,
        1.0,
        1.0,
        1.0,
        1.0,
        1.0,
        1.0,
        1.0,
        1.0,
        1.0,
        1.0,
        1.0,
        1.0,
        1.0,
        1.0,
        1.0,
        1.0,
        1.0,
        1.0,
        1.0,
        1.0,
        1.0,
        1.0,
        1.0,
        1.0,
        1.0,
        1.0,
        1.0,
        1.0,
        1.0,
        1.0,
        1.0,
        1.0,
        1.0,
        1.0,
        1.0,
        1.0,
        1.0,
        1.0,
        1.0,
        1.0,
        1.0,
        1.0,
        1.0,
        1.0,
        2.0,
        1.0,
        1.0,
        1.0,
        1.0,
        1.0,
        1.0,
        2.0,
        1.0,
        2.0
      ],
      "DGDS": [
        -0.000439,
        -4e-06,
        0.0,
        0.0,
        -0.00031,
        -0.000566,
        0.0,
        0.0,
        -0.000252,
        -0.000373,
        -0.000502,
        -0.000572,
        -0.000274,
        -8.9e-05,
        -0.000643,
        0.0,
        -0.000225,
        -0.000216,
        -0.000429,
        0.0,
        0.0,
        0.0,
        0.0,
        0.0,
        -0.00126,
        -0.002168,
        -0.001889,
        -0.000867,
        -0.000132,
        -0.000294,
        -0.000427,
        0.0,
        -0.000283,
        -0.00078,
        0.0,
        0.0,
        -0.000406,
        -0.000437,
        -0.00014,
        0.0,
        -0.000484,
        -0.000306,
        0.0,
        0.0,
        -0.00031,
        -0.000566,
        0.0,
        0.0,
        -0.0006538,
        -0.0006538,
        -0.0006538,
        -0.0006538,
        -0.000283,
        -0.00078,
        0.0,
        0.0,
        0.0,
        0.0,
        0.0,
        0.0,
        0.0,
        0.0,
        0.0,
        0.0,
        -0.0006538,
        -0.0006538,
        -0.0006538,
        -0.0006538,
        0.0,
        0.0,
        0.0,
        0.0,
        0.0,
        0.0,
        0.0,
        0.0,
        0.0,
        0.0,
        0.0,
        0.0,
        0.0,
        0.0,
        0.0,
        0.0,
        0.0,
        0.0,
        0.0,
        0.0,
        -0.000484,
        -0.000306,
        0.0,
        0.0
      ],
      "DGCASP": [
        0.09817,
        -0.21337,
        -0.04562,
        -0.01215,
        0.08277,
        -0.06625,
        0.00325,
        -0.13091,
        -0.12473,
        -0.09976,
        0.17935,
        -0.21337,
        -0.609774,
        -0.12473,
        0.0,
        0.0,
        -0.609774,
        0.0,
        0.0,
        0.0,
        0.0,
        0.0,
        0.17935
      ],
      "DGSASP": [
        0.03876,
        0.0343,
        0.06287,
        -0.04595,
        0.10987,
        0.05534,
        0.12993,
        -0.06038,
        -0.06862,
        0.01192,
        0.13363,
        0.0343,
        -0.01752,
        -0.06862,
        0.0,
        0.0,
        -0.01752,
        0.0,
        0.0,
        0.0,
        0.0,
        0.0,
        0.13363
      ],
      "DGSLOP": [
        -0.17888,
        0.33523,
        0.78176,
        1.17025,
        0.04966,
        0.11931,
        0.46546,
        0.65622,
        0.3007,
        -0.06637,
        0.07628,
        0.33523,
        -2.05706,
        0.3007,
        0.0,
        0.0,
        -2.05706,
        0.0,
        0.0,
        0.0,
        0.0,
        0.0,
        0.07628
      ],
      "DGSLSQ": [
        0.0,
        -0.70216,
        -1.1238,
        -1.52006,
        0.0,
        0.0,
        -0.58014,
        -0.90143,
        -0.62224,
        -0.4372,
        0.0,
        -0.70216,
        2.113263,
        -0.62224,
        0.0,
        0.0,
        2.113263,
        0.0,
        0.0,
        0.0,
        0.0,
        0.0,
        0.0
      ],
      "DGEL": [
        0.03517,
        0.0373,
        0.02591,
        0.00917,
        0.02863,
        -0.00175,
        -0.0048,
        0.06259,
        0.06313,
        0.03229,
        0.08518,
        0.0373,
        0.0,
        0.06313,
        0.0,
        0.0,
        0.0,
        0.0,
        0.0,
        0.0,
        0.0,
        0.0,
        0.08518
      ],
      "DGEL2": [
        -0.000467,
        -0.000433,
        -0.000377,
        -0.000117,
        -0.000422,
        -6.7e-05,
        -5.8e-05,
        -0.000709,
        -0.000676,
        -0.000422,
        -0.000943,
        -0.000433,
        0.0,
        -0.000676,
        0.0,
        0.0,
        0.0,
        0.0,
        0.0,
        0.0,
        0.0,
        0.0,
        -0.000943
      ],
      "HGLD": [
        -0.04935,
        -0.3899,
        -0.4574,
        -0.09775,
        -0.1555,
        -0.1219,
        -0.2454,
        -0.572,
        -0.1997,
        -0.5657,
        -0.1219,
        -0.3899,
        0.0,
        -0.1997,
        0.0,
        0.0,
        0.0,
        0.0,
        0.0,
        0.0,
        0.0,
        0.0,
        -0.1219
      ],
      "BIAS": [
        0.4809
      ],
      "HGLH": [
        0.23315
      ],
      "HGHC": [
        2.03035,
        1.72222,
        1.19728,
        1.81759,
        2.14781,
        1.76998,
        2.21104,
        1.7409
      ],
      "HGLDD": [
        0.62144,
        1.02372,
        0.85493,
        0.75756,
        0.46238,
        0.49643,
        0.37042,
        0.34003
      ],
      "HGH2": [
        -0.00013358,
        -3.809e-05,
        -3.715e-05,
        -2.607e-05,
        -5.2e-05,
        -1.605e-05,
        -3.631e-05,
        -4.46e-05
      ],
      "HGSC": [
        -0.5342,
        0.1433,
        0.1641,
        -0.6458,
        -0.6959,
        -0.9941,
        -0.6004,
        0.2089,
        -0.5478,
        0.7316,
        -0.9941,
        0.1433,
        0.0,
        -0.5478,
        0.0,
        0.0,
        0.0,
        0.0,
        0.0,
        0.0,
        0.0,
        0.0,
        -0.9941
      ],
      "BAMAXA": [
        140.0,
        220.0,
        250.0,
        310.0,
        240.0,
        270.0,
        310.0,
        310.0,
        200.0,
        310.0,
        290.0,
        330.0,
        380.0,
        440.0,
        500.0,
        500.0,
        390.0,
        390.0,
        440.0,
        180.0,
        290.0,
        400.0,
        350.0,
        390.0,
        260.0,
        300.0,
        220.0,
        220.0,
        160.0,
        300.0
      ],
      "MAPSIT": [
        0.0,
        0.0,
        0.0,
        0.0,
        0.0,
        0.0,
        0.0,
        0.0,
        0.0,
        0.0,
        0.0,
        0.0,
        0.0,
        0.0,
        0.0,
        0.0,
        0.0,
        0.0,
        0.0,
        0.0,
        0.0,
        0.0,
        0.0,
        0.0,
        0.0,
        0.0,
        0.0,
        0.0,
        0.0,
        0.0,
        0.0,
        0.0,
        0.0,
        0.0,
        0.0,
        0.0,
        0.0,
        0.0,
        0.0,
        0.0,
        0.0,
        0.0,
        0.0,
        0.0,
        0.0,
        0.0,
        0.0,
        0.0,
        0.0,
        0.0,
        0.0,
        0.0,
        0.0,
        0.0,
        0.0,
        0.0,
        0.0,
        0.0,
        0.0,
        0.0,
        0.0,
        0.0,
        0.0,
        0.0,
        0.0,
        0.0,
        0.0,
        0.0,
        0.0,
        0.0,
        0.0,
        0.0,
        0.0,
        0.0,
        0.0,
        0.0,
        0.0,
        0.0,
        0.0,
        0.0,
        0.0,
        0.0,
        0.0,
        0.0,
        0.0,
        0.0,
        0.0,
        0.0,
        0.0,
        0.0,
        0.0,
        0.0,
        0.0,
        0.0,
        0.0,
        0.0,
        0.0,
        0.0,
        0.0,
        0.0,
        0.0,
        0.0,
        0.0,
        0.0,
        0.0,
        0.0,
        0.0,
        0.0,
        0.0,
        0.0,
        0.0,
        0.0,
        0.0,
        0.0,
        0.0,
        0.0,
        0.0,
        0.0,
        0.0,
        0.0,
        0.0,
        0.0,
        0.0,
        0.0,
        0.0,
        0.0,
        0.0,
        0.0,
        0.0,
        0.0,
        0.0,
        0.0,
        0.0,
        0.0,
        0.0,
        0.0,
        0.0,
        0.0,
        0.0,
        0.0,
        0.0,
        0.0,
        0.0,
        0.0,
        0.0,
        0.0,
        0.0,
        0.0,
        0.0,
        0.0,
        0.0,
        0.0,
        0.0,
        0.0,
        0.0,
        0.0,
        0.0,
        0.0,
        0.0,
        0.0,
        0.0,
        0.0,
        0.0,
        0.0,
        0.0,
        0.0,
        0.0,
        0.0,
        0.0,
        0.0,
        0.0,
        0.0,
        0.0,
        0.0,
        0.0,
        0.0,
        0.0,
        0.0,
        0.0,
        0.0,
        0.0,
        0.0,
        0.0,
        0.0,
        0.0,
        0.0,
        0.0,
        0.0,
        0.0,
        0.0,
        0.0,
        0.0,
        0.0,
        0.0,
        0.0,
        0.0,
        0.0,
        0.0,
        0.0,
        0.0,
        0.0,
        0.0,
        0.0,
        0.0,
        0.0,
        0.0,
        0.0,
        0.0,
        0.0,
        0.0,
        0.0,
        0.0,
        0.0,
        0.0,
        0.0,
        0.0,
        0.0,
        0.0,
        0.0,
        0.0,
        0.0,
        0.0,
        0.0,
        0.0,
        0.0,
        0.0,
        0.0,
        0.0,
        0.0,
        0.0,
        0.0,
        0.0,
        0.0,
        0.0,
        0.0,
        0.0,
        0.0,
        0.0,
        0.0,
        0.0,
        0.0,
        0.0,
        0.0,
        0.0,
        0.0,
        0.0,
        0.0,
        0.0,
        0.0,
        0.0,
        0.0,
        0.0,
        0.0,
        0.0,
        0.0,
        0.0,
        0.0,
        0.0,
        0.0,
        0.0,
        0.0,
        0.0,
        0.0,
        0.0,
        0.0,
        0.0,
        0.0,
        0.0,
        0.0,
        0.0,
        0.0,
        0.0,
        0.0,
        0.0,
        0.0,
        0.0,
        0.0,
        0.0,
        0.0,
        0.0,
        0.0,
        0.0,
        0.0,
        0.0,
        0.0,
        0.0,
        0.0,
        0.0,
        0.0,
        0.0,
        0.0,
        0.0,
        0.0,
        0.0,
        0.0,
        0.0,
        0.0,
        0.0,
        0.0,
        0.0,
        0.0,
        0.0,
        0.0,
        0.0,
        0.0,
        0.0,
        0.0,
        0.0,
        0.0,
        0.0,
        0.0,
        0.0,
        0.0,
        0.0,
        0.0,
        0.0,
        0.0,
        0.0,
        0.0,
        0.0,
        0.0,
        0.0,
        0.0,
        0.0,
        0.0,
        0.0,
        0.0,
        0.0,
        0.0,
        0.0,
        0.0,
        0.0,
        0.0,
        0.0,
        0.0,
        0.0,
        0.0,
        0.0,
        0.0,
        0.0,
        0.0,
        0.0,
        0.0,
        0.0,
        0.0,
        0.0,
        0.0,
        0.0,
        0.0,
        0.0,
        0.0,
        0.0,
        0.0,
        0.0,
        0.0,
        0.0,
        0.0,
        0.0,
        0.0,
        0.0,
        29.0,
        35.0,
        35.0,
        32.0,
        34.0,
        35.0,
        32.0,
        27.0,
        39.0,
        37.0,
        32.0,
        36.0,
        41.0,
        41.0,
        41.0,
        38.0,
        39.0,
        32.0,
        36.0,
        34.0,
        34.0,
        32.0,
        36.0,
        36.0,
        36.0,
        26.0,
        22.0,
        26.0,
        0.0,
        0.0,
        0.0,
        0.0,
        0.0,
        0.0,
        0.0,
        0.0,
        0.0,
        0.0,
        0.0,
        0.0,
        0.0,
        0.0,
        0.0,
        0.0,
        0.0,
        0.0,
        0.0,
        0.0,
        0.0,
        0.0,
        0.0,
        0.0,
        0.0,
        0.0,
        0.0,
        0.0,
        0.0,
        0.0,
        9.0,
        13.0,
        12.0,
        10.0,
        12.0,
        12.0,
        11.0,
        8.0,
        14.0,
        11.0,
        13.0,
        16.0,
        15.0,
        15.0,
        15.0,
        14.0,
        14.0,
        11.0,
        12.0,
        13.0,
        13.0,
        11.0,
        13.0,
        13.0,
        13.0,
        8.0,
        6.0,
        8.0,
        6.0,
        8.0,
        10.0,
        10.0,
        9.0,
        10.0,
        10.0,
        9.0,
        7.0,
        11.0,
        9.0,
        11.0,
        12.0,
        12.0,
        12.0,
        12.0,
        11.0,
        11.0,
        9.0,
        10.0,
        10.0,
        10.0,
        9.0,
        10.0,
        10.0,
        10.0,
        7.0,
        6.0,
        7.0,
        25.0,
        29.0,
        35.0,
        35.0,
        33.0,
        34.0,
        35.0,
        32.0,
        27.0,
        39.0,
        37.0,
        32.0,
        36.0,
        41.0,
        41.0,
        41.0,
        38.0,
        39.0,
        32.0,
        36.0,
        34.0,
        34.0,
        32.0,
        36.0,
        36.0,
        36.0,
        26.0,
        22.0,
        26.0,
        36.0,
        43.0,
        51.0,
        50.0,
        44.0,
        49.0,
        48.0,
        46.0,
        41.0,
        55.0,
        46.0,
        52.0,
        59.0,
        58.0,
        58.0,
        58.0,
        54.0,
        55.0,
        46.0,
        49.0,
        52.0,
        52.0,
        46.0,
        52.0,
        52.0,
        52.0,
        38.0,
        33.0,
        38.0,
        44.0,
        57.0,
        76.0,
        62.0,
        72.0,
        72.0,
        71.0,
        67.0,
        55.0,
        86.0,
        67.0,
        80.0,
        95.0,
        93.0,
        93.0,
        93.0,
        84.0,
        86.0,
        67.0,
        73.0,
        80.0,
        80.0,
        67.0,
        80.0,
        80.0,
        80.0,
        49.0,
        36.0,
        49.0,
        36.0,
        43.0,
        51.0,
        50.0,
        44.0,
        49.0,
        48.0,
        46.0,
        41.0,
        55.0,
        46.0,
        52.0,
        59.0,
        58.0,
        58.0,
        58.0,
        54.0,
        55.0,
        46.0,
        49.0,
        52.0,
        52.0,
        46.0,
        52.0,
        52.0,
        52.0,
        38.0,
        33.0,
        38.0,
        36.0,
        43.0,
        51.0,
        50.0,
        44.0,
        49.0,
        48.0,
        46.0,
        41.0,
        55.0,
        46.0,
        52.0,
        59.0,
        58.0,
        58.0,
        58.0,
        54.0,
        55.0,
        46.0,
        49.0,
        52.0,
        52.0,
        46.0,
        52.0,
        52.0,
        52.0,
        38.0,
        33.0,
        38.0,
        44.0,
        57.0,
        76.0,
        62.0,
        72.0,
        72.0,
        71.0,
        67.0,
        55.0,
        86.0,
        67.0,
        80.0,
        95.0,
        93.0,
        93.0,
        93.0,
        84.0,
        86.0,
        67.0,
        73.0,
        80.0,
        80.0,
        67.0,
        80.0,
        80.0,
        80.0,
        49.0,
        36.0,
        49.0,
        0.0,
        0.0,
        0.0,
        0.0,
        0.0,
        0.0,
        0.0,
        0.0,
        0.0,
        0.0,
        0.0,
        0.0,
        0.0,
        0.0,
        0.0,
        0.0,
        0.0,
        0.0,
        0.0,
        0.0,
        0.0,
        0.0,
        0.0,
        0.0,
        0.0,
        0.0,
        0.0,
        0.0,
        0.0,
        0.0
      ],
      "MAPSS": [
        10.0,
        10.0,
        3.0,
        3.0,
        3.0,
        3.0,
        3.0,
        3.0,
        3.0,
        8.0,
        8.0,
        4.0,
        4.0,
        6.0,
        6.0,
        6.0,
        5.0,
        9.0,
        9.0,
        9.0,
        9.0,
        9.0,
        11.0,
        9.0,
        11.0,
        9.0,
        9.0,
        9.0,
        12.0,
        3.0
      ],
      "TREFMT": [
        "(I4,T1,I7,F6.0,I1,A3,F4.1,F3.1,2F3.0,F4.1,I1,3(I2,I2),2I1,I2,2I3,  2I1,F3.0)"
      ]
    }
  }
}